cdisco/color_analysis.py
cdisco/datasets.py
cdisco/predict.py
scripts/analyze.py
scripts/cdisco.py
scripts/color_analysis.py
scripts/datasets.py
scripts/predict.py
scripts/utils.py
scripts/vis.py
cdisco-0.1.1.dist-info/LICENSE.txt
cdisco-0.1.1.dist-info/METADATA
cdisco-0.1.1.dist-info/WHEEL
cdisco-0.1.1.dist-info/top_level.txt
cdisco-0.1.1.dist-info/RECORD
