Metadata-Version: 2.1
Name: cdisco
Version: 0.1.1
Summary: Concept discovery with Singular Value Decomposition
Home-page: https://github.com/maragraziani/cdisco
Author: Mara Graziani
Author-email: mara.graziani@hevs.ch
License: MIT
Platform: UNKNOWN
Classifier: Development Status :: 1 - Planning
Classifier: Intended Audience :: Science/Research
Classifier: License :: OSI Approved :: BSD License
Classifier: Operating System :: POSIX :: Linux
Classifier: Programming Language :: Python :: 2
Classifier: Programming Language :: Python :: 2.7
Classifier: Programming Language :: Python :: 3
Classifier: Programming Language :: Python :: 3.4
Classifier: Programming Language :: Python :: 3.5
License-File: LICENSE.txt
Requires-Dist: matplotlib
Requires-Dist: numpy
Requires-Dist: scikit-learn ==1.2.2
Requires-Dist: torch ==2.0.1
Requires-Dist: torchvision ==0.15.2
